Nevzat_Probability-0.1.dist-info/DESCRIPTION.rst
Nevzat_Probability-0.1.dist-info/METADATA
Nevzat_Probability-0.1.dist-info/RECORD
Nevzat_Probability-0.1.dist-info/WHEEL
Nevzat_Probability-0.1.dist-info/metadata.json
Nevzat_Probability-0.1.dist-info/top_level.txt
distributions/Binomialdistribution.py
distributions/Gaussiandistribution.py
distributions/Generaldistribution.py
distributions/__init__.py
